rootlab_lib/__init__.py
rootlab_lib/arduino.py
rootlab_lib/instron_analysis.py
rootlab_lib/mark10_analysis.py
rootlab_lib/multilayer_reader.py
rootlab_lib/plateau_processing.py
rootlab_lib/serial_reader.py
rootlab_lib/source_meter_analysis.py
rootlab_lib/vkx150_analysis.py
rootlab_lib/voltage_analysis.py
rootlab_lib-0.8.2.dist-info/licenses/LICENSE
rootlab_lib-0.8.2.dist-info/METADATA
rootlab_lib-0.8.2.dist-info/WHEEL
rootlab_lib-0.8.2.dist-info/top_level.txt
rootlab_lib-0.8.2.dist-info/RECORD
