Metadata-Version: 2.4
Name: rootlab_lib
Version: 0.8.2
Summary: RootLab data analysis tools
Author-email: Trevor Swan <tcs94@case.edu>, Samuel Root <ser132@case.edu>
License-Expression: MIT
Project-URL: Homepage, https://github.com/trevorswan11/rootlab-lib
Project-URL: Issues, https://github.com/trevorswan11/rootlab-lib/issues
Classifier: Programming Language :: Python :: 3
Classifier: Operating System :: OS Independent
Requires-Python: >=3.7
License-File: LICENSE
Requires-Dist: matplotlib
Requires-Dist: numpy
Requires-Dist: pandas
Requires-Dist: scipy
Requires-Dist: pyserial
Requires-Dist: opencv-python
Dynamic: license-file
